get_user_agent_pls/__init__.py
get_user_agent_pls/get_user_agent_pls.py
get_user_agent_pls/get_user_agent_pls_scraper.py
get_user_agent_pls/test_get_user_agent_pls.py
get_user_agent_pls-1.dist-info/LICENSE
get_user_agent_pls-1.dist-info/METADATA
get_user_agent_pls-1.dist-info/WHEEL
get_user_agent_pls-1.dist-info/entry_points.txt
get_user_agent_pls-1.dist-info/top_level.txt
get_user_agent_pls-1.dist-info/RECORD
