Metadata-Version: 2.1
Name: get-user-agent-pls
Version: 1
Summary: A package to fetch get-user-agent strings
Home-page: https://github.com/djh00t/get-user-agent-pls
Author: David Hooton
Author-email: get_user_agent_pls@hooton.org
Classifier: Programming Language :: Python :: 3
Classifier: License :: OSI Approved :: MIT License
Classifier: Operating System :: OS Independent
Requires-Python: >=3.6
License-File: LICENSE
Requires-Dist: requests
Requires-Dist: beautifulsoup4
